cloudquery_plugin_sdk-0.1.50-py3.13-nspkg.pth
cloudquery/sdk/__init__.py
cloudquery/sdk/py.typed
cloudquery/sdk/internal/__init__.py
cloudquery/sdk/internal/memdb/__init__.py
cloudquery/sdk/internal/memdb/memdb.py
cloudquery/sdk/internal/servers/__init__.py
cloudquery/sdk/internal/servers/discovery_v1/__init__.py
cloudquery/sdk/internal/servers/discovery_v1/discovery.py
cloudquery/sdk/internal/servers/plugin_v3/__init__.py
cloudquery/sdk/internal/servers/plugin_v3/plugin.py
cloudquery/sdk/message/__init__.py
cloudquery/sdk/message/read.py
cloudquery/sdk/message/sync.py
cloudquery/sdk/message/write.py
cloudquery/sdk/plugin/__init__.py
cloudquery/sdk/plugin/plugin.py
cloudquery/sdk/scalar/__init__.py
cloudquery/sdk/scalar/binary.py
cloudquery/sdk/scalar/bool.py
cloudquery/sdk/scalar/date32.py
cloudquery/sdk/scalar/date64.py
cloudquery/sdk/scalar/float.py
cloudquery/sdk/scalar/int.py
cloudquery/sdk/scalar/json.py
cloudquery/sdk/scalar/list.py
cloudquery/sdk/scalar/scalar.py
cloudquery/sdk/scalar/scalar_factory.py
cloudquery/sdk/scalar/string.py
cloudquery/sdk/scalar/timestamp.py
cloudquery/sdk/scalar/uint.py
cloudquery/sdk/scalar/uuid.py
cloudquery/sdk/scalar/vector.py
cloudquery/sdk/scheduler/__init__.py
cloudquery/sdk/scheduler/scheduler.py
cloudquery/sdk/scheduler/table_resolver.py
cloudquery/sdk/schema/__init__.py
cloudquery/sdk/schema/arrow.py
cloudquery/sdk/schema/column.py
cloudquery/sdk/schema/resource.py
cloudquery/sdk/schema/table.py
cloudquery/sdk/serve/__init__.py
cloudquery/sdk/serve/plugin.py
cloudquery/sdk/stateclient/__init__.py
cloudquery/sdk/stateclient/stateclient.py
cloudquery/sdk/transformers/__init__.py
cloudquery/sdk/transformers/openapi.py
cloudquery/sdk/transformers/transformers.py
cloudquery/sdk/types/__init__.py
cloudquery/sdk/types/json.py
cloudquery/sdk/types/uuid.py
cloudquery_plugin_sdk-0.1.50.dist-info/licenses/LICENSE
cloudquery_plugin_sdk-0.1.50.dist-info/METADATA
cloudquery_plugin_sdk-0.1.50.dist-info/WHEEL
cloudquery_plugin_sdk-0.1.50.dist-info/namespace_packages.txt
cloudquery_plugin_sdk-0.1.50.dist-info/top_level.txt
cloudquery_plugin_sdk-0.1.50.dist-info/RECORD
