Metadata-Version: 2.4
Name: cloudquery-plugin-sdk
Version: 0.1.50
Summary: CloudQuery Plugin SDK for Python
Home-page: https://github.com/cloudquery/plugin-sdk-python
Author: CloudQuery LTD
Author-email: pypi-packages@cloudquery.io
License: MPL-2.0
Platform: Posix; MacOS X; Windows
Classifier: Intended Audience :: Developers
Classifier: License :: OSI Approved :: Apache Software License
Classifier: Programming Language :: Python
Classifier: Programming Language :: Python :: 3
Classifier: Programming Language :: Python :: 3.7
Classifier: Programming Language :: Python :: 3.8
Classifier: Programming Language :: Python :: 3.9
Classifier: Programming Language :: Python :: 3.10
Classifier: Programming Language :: Python :: 3.11
Classifier: Operating System :: OS Independent
Classifier: Topic :: Internet
Requires-Python: >=3.7
License-File: LICENSE
Requires-Dist: cloudquery-plugin-pb==0.0.49
Requires-Dist: exceptiongroup==1.3.0
Requires-Dist: black==25.9.0
Requires-Dist: grpcio==1.75.1
Requires-Dist: grpcio-tools==1.75.1
Requires-Dist: iniconfig==2.1.0
Requires-Dist: Jinja2==3.1.6
Requires-Dist: MarkupSafe==3.0.3
Requires-Dist: numpy==2.3.3
Requires-Dist: packaging==25.0
Requires-Dist: pandas==2.3.3
Requires-Dist: pluggy==1.6.0
Requires-Dist: protobuf>=6.31.1
Requires-Dist: pyarrow==21.0.0
Requires-Dist: pytest==8.4.2
Requires-Dist: python-dateutil>=2.8.1
Requires-Dist: pytz==2025.2
Requires-Dist: six==1.17.0
Requires-Dist: structlog==25.4.0
Requires-Dist: tomli==2.2.1
Requires-Dist: tzdata==2025.2
Dynamic: author
Dynamic: author-email
Dynamic: classifier
Dynamic: description
Dynamic: home-page
Dynamic: license
Dynamic: license-file
Dynamic: platform
Dynamic: requires-dist
Dynamic: requires-python
Dynamic: summary
